foundation_model_pkg/__init__.py
foundation_model_pkg/foundation_model.py
foundation_model_pkg/tools/__init__.py
foundation_model_pkg/tools/foundation_model.py
foundation_model_pkg/tools/utils.py
foundation_model_pkg/yamls/foundation_model.yaml
tests/__init__.py
tests/test_my_tool_1.py
foundation_model_tool-0.0.8.dist-info/METADATA
foundation_model_tool-0.0.8.dist-info/WHEEL
foundation_model_tool-0.0.8.dist-info/entry_points.txt
foundation_model_tool-0.0.8.dist-info/top_level.txt
foundation_model_tool-0.0.8.dist-info/RECORD
